cybertek_api/__init__.py
cybertek_api/cybertek_api.py
cybertek_api-0.0.1.dist-info/LICENSE
cybertek_api-0.0.1.dist-info/METADATA
cybertek_api-0.0.1.dist-info/WHEEL
cybertek_api-0.0.1.dist-info/top_level.txt
cybertek_api-0.0.1.dist-info/RECORD
